Metadata-Version: 2.1
Name: testeetestee
Version: 0.3
Summary: justaquicktest
Author: Charlie Gaynor
Author-email: charliejackcoding@gmail.com
Requires-Python: >=3.10.1
